emtools/__init__.py
emtools/hpc/__init__.py
emtools/hpc/__main__.py
emtools/hpc/lsf.py
emtools/hpc/submit.py
emtools/image/__init__.py
emtools/image/thumbnail.py
emtools/jobs/__init__.py
emtools/jobs/batch_manager.py
emtools/jobs/pipeline.py
emtools/metadata/__init__.py
emtools/metadata/epu.py
emtools/metadata/misc.py
emtools/metadata/sqlite.py
emtools/metadata/starfile.py
emtools/metadata/table.py
emtools/pwx/__init__.py
emtools/pwx/monitors.py
emtools/pwx/workflow.py
emtools/scripts/__init__.py
emtools/scripts/emt-change-optics.py
emtools/scripts/emt-frames.py
emtools/scripts/emt-scipion-apo.py
emtools/scripts/emt-scipion-otf.py
emtools/scripts/emt_angdist.py
emtools/scripts/emt_beamshifts.py
emtools/scripts/emt_epu.py
emtools/scripts/emt_files.py
emtools/scripts/emt_ps.py
emtools/tests/__init__.py
emtools/tests/star_pipeline_tester.py
emtools/tests/test_metadata.py
emtools/tests/test_pipeline.py
emtools/tests/test_utils.py
emtools/utils/__init__.py
emtools/utils/color.py
emtools/utils/path.py
emtools/utils/pretty.py
emtools/utils/process.py
emtools/utils/server.py
emtools/utils/system.py
emtools/utils/time.py
emtools-0.1.3.data/scripts/emt-scipion-otf.py
emtools-0.1.3.dist-info/LICENSE
emtools-0.1.3.dist-info/METADATA
emtools-0.1.3.dist-info/WHEEL
emtools-0.1.3.dist-info/entry_points.txt
emtools-0.1.3.dist-info/top_level.txt
emtools-0.1.3.dist-info/RECORD
